runespreader/__init__.py
runespreader/bot.py
runespreader/clickhouse.py
runespreader/consumer.py
runespreader/publisher.py
runespreader/spreader.py
runespreader/spreadfinder.py
runespreader-0.3.0.dist-info/METADATA
runespreader-0.3.0.dist-info/WHEEL
runespreader-0.3.0.dist-info/entry_points.txt
runespreader-0.3.0.dist-info/RECORD
