Metadata-Version: 2.1
Name: runespreader
Version: 0.3.0
Summary: 
Author: Charles Warren
Author-email: ciwarren@mtu.edu
Requires-Python: >=3.11,<4.0
Classifier: Programming Language :: Python :: 3
Classifier: Programming Language :: Python :: 3.11
Requires-Dist: clickhouse-driver (>=0.2.6,<0.3.0)
Requires-Dist: discord (>=2.3.2,<3.0.0)
Requires-Dist: faust-streaming (>=0.11.1,<0.12.0)
Requires-Dist: kafka-python (>=2.0.2,<3.0.0)
Requires-Dist: pandas (>=2.0.3,<3.0.0)
Requires-Dist: pyyaml (>=6.0.1,<7.0.0)
Requires-Dist: requests (>=2.32.3,<3.0.0)
Requires-Dist: structlog (>=24.2.0,<25.0.0)
Requires-Dist: twisted (>=24.3.0,<25.0.0)
